pyfastcli/__init__.py
pyfastcli/cli.py
pyfastcli-0.1.0.dist-info/METADATA
pyfastcli-0.1.0.dist-info/WHEEL
pyfastcli-0.1.0.dist-info/entry_points.txt
pyfastcli-0.1.0.dist-info/top_level.txt
pyfastcli-0.1.0.dist-info/RECORD
