Metadata-Version: 2.4
Name: pyfastcli
Version: 0.1.0
Summary: CLI pour générer des fichiers Python et routes Django Ninja
Author-email: Hedi <hedi@example.com>
License: MIT
Project-URL: Homepage, https://github.com/hedi/pyfastcli
Project-URL: Repository, https://github.com/hedi/pyfastcli
Project-URL: Issues, https://github.com/hedi/pyfastcli/issues
Keywords: cli,code-generator,django,ninja,scaffolding
Classifier: Programming Language :: Python :: 3
Classifier: Programming Language :: Python :: 3.8
Classifier: Programming Language :: Python :: 3.9
Classifier: Programming Language :: Python :: 3.10
Classifier: Programming Language :: Python :: 3.11
Classifier: Programming Language :: Python :: 3.12
Classifier: License :: OSI Approved :: MIT License
Classifier: Operating System :: OS Independent
Classifier: Topic :: Software Development :: Code Generators
Requires-Python: >=3.8
Requires-Dist: click>=8.0.0
Provides-Extra: dev
Requires-Dist: pytest>=7.4.0; extra == "dev"
Requires-Dist: pytest-cov>=4.1.0; extra == "dev"
Requires-Dist: black>=23.0.0; extra == "dev"
Requires-Dist: ruff>=0.1.0; extra == "dev"
Requires-Dist: mypy>=1.5.0; extra == "dev"
Requires-Dist: ipdb>=0.13.0; extra == "dev"
Provides-Extra: django
Requires-Dist: django>=4.0.0; extra == "django"
Provides-Extra: django-ninja
Requires-Dist: django-ninja>=1.0.0; extra == "django-ninja"
Provides-Extra: django-drf
Requires-Dist: djangorestframework>=3.14.0; extra == "django-drf"
Provides-Extra: django-all
Requires-Dist: django>=4.0.0; extra == "django-all"
Requires-Dist: django-ninja>=1.0.0; extra == "django-all"
Requires-Dist: djangorestframework>=3.14.0; extra == "django-all"
